LICENSE
README.md
setup.cfg
setup.py
geochatt/__init__.py
geochatt/city_council_districts.geojson
geochatt/intersections.csv.gz
geochatt/live_parcels.csv.gz
geochatt/municipalities.geojson
geochatt/neighborhoods.csv.gz
geochatt/old_city_council_districts.geojson
geochatt/zipcodes.geojson
geochatt.egg-info/PKG-INFO
geochatt.egg-info/SOURCES.txt
geochatt.egg-info/dependency_links.txt
geochatt.egg-info/entry_points.txt
geochatt.egg-info/requires.txt
geochatt.egg-info/top_level.txt