Metadata-Version: 2.4
Name: geochatt
Version: 0.3.1
Summary: Utility Functions for Working with Open GeoSpatial Data about Chattanooga
Home-page: https://github.com/officeofperformancemanagement/geochatt
Download-URL: https://github.com/officeofperformancemanagement/geochatt/tarball/download
Author: Daniel J. Dufour
Author-email: daniel.j.dufour@gmail.com
Keywords: data,python
Classifier: Development Status :: 4 - Beta
Classifier: Programming Language :: Python :: 3
Classifier: License :: CC0 1.0 Universal (CC0 1.0) Public Domain Dedication
Classifier: Operating System :: OS Independent
License-File: LICENSE
Requires-Dist: shapely
Dynamic: author
Dynamic: author-email
Dynamic: classifier
Dynamic: description
Dynamic: description-content-type
Dynamic: download-url
Dynamic: home-page
Dynamic: keywords
Dynamic: license-file
Dynamic: requires-dist
Dynamic: summary
